{ 
  "Missing-Person" : [

       {
         "id": 0,
         "Name": "Fabian Robinson",
         "Gender": "Male",
         "Age": "40-years-old",
         "imageUrl": "https://jcf.gov.jm/wp-content/uploads/2021/09/Fabian-Robinson-Web-495x400.jpg" },

       {
         "id": 1,
         "Name": "Delgardo Richards",
         "Gender": "Male",
         "Age": "14-years-old",
         "imageUrl": "https://jcf.gov.jm/wp-content/uploads/2021/09/Delgardo-Richards-Web-495x400.jpg" },

       {
          "id": 2,
          "Name": "Shaniel McLean",
          "Gender": "Female",
          "Age": "14-years-old",
          "imageUrl": "https://jcf.gov.jm/wp-content/uploads/2021/09/Shaniel-McLean-Web-495x400.jpg" },
        
        {
          "id": 3,
          "Name": "Lakeisha Campbell",
          "Gender": "Female",
          "Age": "37-years-old",
          "imageUrl": "https://jcf.gov.jm/wp-content/uploads/2021/09/Lakeisha-Campbell-Web-495x400.jpg" },

        {
          "id": 4,
          "Name": "Anthony Swaby",
          "Gender": "Male",
          "Age": "70-years-old",
          "imageUrl": "https://jcf.gov.jm/wp-content/uploads/2021/09/Anthony-Swaby-Web-495x400.jpg" },

        {
          "id": 5,
          "Name": "Chevon Dixon",
          "Gender": "Male",
          "Age": "16-years-old",
          "imageUrl": "https://jcf.gov.jm/wp-content/uploads/2021/09/Chevon-Dixon-Web-495x400.jpg" },
              
        {
          "id": 6,
          "Name": "Andrew Richards",
          "Gender": "Male",
          "Age": "54-years-old",
          "imageUrl": "https://jcf.gov.jm/wp-content/uploads/2021/09/Andrew-Richards-Web-495x400.jpg" },

        {
          "id": 7,
          "Name": "Tiffany Jervis",
          "Gender": "Female",
          "Age": "14-years-old",
          "imageUrl": "https://jcf.gov.jm/wp-content/uploads/2021/09/Tiffany-Jervis-Web-495x400.jpg" },
              
        {
          "id": 8,
          "Name": "Kenroy Cunningham",
          "Gender": "Male",
          "Age": "13-years-old",
          "imageUrl": "https://jcf.gov.jm/wp-content/uploads/2021/08/Kenroy-Cunningham-Web-495x400.jpg" },
              
        {
          "id": 9,
          "Name": "Christal Keane",
          "Gender": "Female",
          "Age": "16-years-old",
          "imageUrl": "https://jcf.gov.jm/wp-content/uploads/2021/08/Christal-Keane-Web-495x400.jpg" },

        {
          "id": 10,
          "Name": "Kara Campbell",
          "Gender": "Female",
          "Age": "15-years-old",
          "imageUrl": "https://jcf.gov.jm/wp-content/uploads/2021/08/Kara-Campbell-Web-495x400.jpg" },
        {
          "id": 11,
          "Name": "Jinel Jennings",
          "Gender": "Female",
          "Age": "16-years-old",
          "imageUrl": "https://jcf.gov.jm/wp-content/uploads/2021/08/Jinel-Jennings-Web-495x400.jpg" },

        {
          "id": 12,
          "Name": "Anthony Hayles",
          "Gender": "Male",
          "Age": "31-years-old",
          "imageUrl": "https://jcf.gov.jm/wp-content/uploads/2021/08/Anthony-Hayles-495x400.jpg" },

        {
          "id": 13,
          "Name": "Sabrina Graham",
          "Gender": "Female",
          "Age": "24-years-old",
          "imageUrl": "https://jcf.gov.jm/wp-content/uploads/2021/08/Sabrina-Graham-Web-495x400.jpg" },
        {
          "id": 14,
          "Name": "Christina Pinnock",
          "Gender": "Female",
          "Age": "14-years-old",
          "imageUrl": "https://jcf.gov.jm/wp-content/uploads/2021/08/Christina-Pinnock-Web-495x400.jpg" },

        {
          "id": 15,
          "Name": "Serina Williams",
          "Gender": "Female",
          "Age": "14-years-old",
          "imageUrl": "https://jcf.gov.jm/wp-content/uploads/2021/08/Serina-Williams-Web-495x400.jpg" }
  
  ]

}


